huoshui_fetch/__init__.py
huoshui_fetch/__main__.py
huoshui_fetch/utils.py
huoshui_fetch/tools/__init__.py
huoshui_fetch/tools/converters.py
huoshui_fetch/tools/extractors.py
huoshui_fetch/tools/fetchers.py
huoshui_fetch-0.1.2.dist-info/METADATA
huoshui_fetch-0.1.2.dist-info/WHEEL
huoshui_fetch-0.1.2.dist-info/entry_points.txt
huoshui_fetch-0.1.2.dist-info/licenses/LICENSE
huoshui_fetch-0.1.2.dist-info/RECORD
