Metadata-Version: 2.4
Name: huoshui-fetch
Version: 0.1.2
Summary: A dedicated web content fetching and conversion service based on the MCP philosophy.
Author-email: huoshui ai <service@huoshuiai.com>
License: MIT
License-File: LICENSE
Requires-Python: >=3.11
Requires-Dist: beautifulsoup4>=4.12.0
Requires-Dist: fastmcp>=0.1.0
Requires-Dist: httpx>=0.27.0
Requires-Dist: lxml>=5.0.0
Requires-Dist: markdownify>=0.11.0
Requires-Dist: pydantic>=2.0.0
Requires-Dist: readability-lxml>=0.8.1
